Metadata-Version: 2.1
Name: ojitos369-ftp
Version: 0.1
Summary: Funciones con conexiones a bases de datos
Home-page: https://github.com/Ojitos369/ojitos369-pip
Author: Ojitos369
Author-email: ojitos369@gmail.com
License: LGPL v3
Keywords: Utilidades de ojitos369
Classifier: Programming Language :: Python
Classifier: Programming Language :: Python :: 3.6
Classifier: Programming Language :: Python :: 3.7
Classifier: Programming Language :: Python :: 3.8
Classifier: Programming Language :: Python :: 3.9
Classifier: Programming Language :: Python :: 3.10
License-File: LICENSE.txt
